LICENSE
README.md
setup.py
ebay_listings_scraper/__init__.py
ebay_listings_scraper.egg-info/PKG-INFO
ebay_listings_scraper.egg-info/SOURCES.txt
ebay_listings_scraper.egg-info/dependency_links.txt
ebay_listings_scraper.egg-info/requires.txt
ebay_listings_scraper.egg-info/top_level.txt