Metadata-Version: 2.1
Name: ebay-listings-scraper
Version: 1.0.2
Summary: A python library to scrape ebay, listing title, rating, condition, price, shipping, listing link
Home-page: UNKNOWN
Author: DataKund
Author-email: datakund@gmail.com
License: Apache License 2.0
Keywords: ebay e-bay python bot_studio automation search scraper scrape listing title rating condition price shipping listing_link
Platform: UNKNOWN
License-File: LICENSE
